spexod/FITSREAD.md
spexod/__init__.py
spexod/api.py
spexod/filepaths.py
spexod/fits_read.py
spexod-0.2.1.data/data/spexod/FITSREAD.md
spexod-0.2.1.dist-info/LICENSE
spexod-0.2.1.dist-info/METADATA
spexod-0.2.1.dist-info/WHEEL
spexod-0.2.1.dist-info/top_level.txt
spexod-0.2.1.dist-info/RECORD
